pyajazz/__init__.py
pyajazz/core.py
pyajazz/inputs.py
pyajazz/protocol.py
pyajazz-0.1.1.dist-info/licenses/LICENSE
pyajazz-0.1.1.dist-info/METADATA
pyajazz-0.1.1.dist-info/WHEEL
pyajazz-0.1.1.dist-info/top_level.txt
pyajazz-0.1.1.dist-info/RECORD
