Metadata-Version: 2.4
Name: pyajazz
Version: 0.1.1
Summary: Python interface for a USB Ajazz stream controllers
Author-email: Marcin Perdeusz <superdee2137@gmail.com>
Project-URL: Homepage, https://github.com/superdeee/pyajazz
Project-URL: Bug Tracker, https://github.com/superdeee/pyajazz/issues
Classifier: Intended Audience :: Developers
Classifier: Operating System :: OS Independent
Classifier: Programming Language :: Python :: 3
Classifier: License :: OSI Approved :: MIT License
Requires-Python: >=3.10
License-File: LICENSE
Requires-Dist: hidapi>=0.14.0
Dynamic: license-file
